wildcard_matcher/__init__.py
wildcard_matcher/py.typed
wildcard_matcher-0.0.3.dist-info/WHEEL
wildcard_matcher-0.0.3.dist-info/METADATA
wildcard_matcher-0.0.3.dist-info/RECORD
