Metadata-Version: 2.1
Name: wildcard-matcher
Version: 0.0.3
Summary: A simple wildcard string matcher
Home-page: https://github.com/yaleman/wildcard_matcher
License: MIT
Author: James Hodgkinson
Author-email: james@terminaloutcomes.com
Requires-Python: >=3.7,<4.0
Classifier: License :: OSI Approved :: MIT License
Classifier: Programming Language :: Python :: 3
Classifier: Programming Language :: Python :: 3.10
Classifier: Programming Language :: Python :: 3.7
Classifier: Programming Language :: Python :: 3.8
Classifier: Programming Language :: Python :: 3.9
Project-URL: Repository, https://github.com/yaleman/wildcard_matcher
